Workbook

Sheet Mode emploi
A1: Fiches de travail – Protéger les données personnelles (BTS SIO SISR, séances 1 et 2)
A2: Classeur à remplir · importable dans Excel, Google Sheets ou LibreOffice
B4: COMMENT TRAVAILLER
B5: 1. Remplissez les onglets avec les menus déroulants (cases jaunes).
B6: 2. Enregistrez le fichier sous votre nom (ex. : Durand_FitZone.xlsx) et déposez-le.
B8: LÉGENDE
B9: Cases jaunes : à remplir (menus déroulants ▼). Cases bleues : calculées automatiquement. Ligne grise en italique : exemple, à ne pas modifier.
B10: Dans les menus « exemples », vous pouvez aussi saisir votre propre réponse. Pour Catégorie, P, G, Critère et Qualification, seule une valeur de la liste est acceptée.
B12: ONGLETS
B13: Qualif et classement · Classif · A Cartographie · B Risques · C Plan · Matrice 5x5 · Listes
B15: RÈGLES DE COTATION
B16: Criticité C = Probabilité P × Gravité G (échelle 1 à 5). Seuil d’acceptabilité : C ≥ 10.
B17: 1–4 Faible · 5–9 À surveiller · 10–14 À traiter · 15–25 Prioritaire
B19: IMPORTER LE FICHIER
... B21: Fil rouge : étude de cas FitZone (réseau de 3 salles de sport, 45 salariés, environ 6 000 abonnés).

Sheet Qualif et classement
A1: Exercices rapides : qualification et classement
A2: Menus déroulants stricts
A4: 1. Qualification d’une donnée (5 min)
A5: Réf. | B5: Information à qualifier | C5: Réponse
A6: Ex. | B6: Un numéro de téléphone mobile nominatif | C6: DCP
A7: a | B7: L’adresse IP d’un visiteur
A8: b | B8: Un arrêt maladie dans un dossier RH
A9: c | B9: La moyenne de ventes par magasin
A10: d | B10: L’empreinte digitale utilisée pour badger
A11: e | B11: L’identifiant haché d’un client
A14: 2. Classement d’incidents (5 min)
A15: Réf. | B15: Incident | C15: Menace ANSSI | D15: Critère touché
A16: Ex. | B16: Un site de partenaire visité par vos salariés est piégé | C16: Espionnage | D16: Confidentialité
A17: a | B17: Le site de la mairie est remplacé par un message politique
A18: b | B18: Un faux e-mail « de la DRH » contient un avenant piégé
A19: c | B19: La base RH est chiffrée contre rançon
A20: d | B20: Un site de sous-traitant, consulté par vos salariés, a été piégé

Sheet Classif
A1: Classification de l’information
A2: Choisissez la catégorie puis jusqu’à 3 services autorisés (menus déroulants). Divulgable ≈ 80 %, Sensible ≈ 15 %, Stratégique ≈ 5 %.
A3: Lignes complètes : | B3: =SUMPRODUCT((B6:B18<>"")*(C6:C18<>""))&" / 13" -> 0 / 13
A4: Information | B4: Catégorie | C4: Accès 1 | D4: Accès 2 | E4: Accès 3
A5: Ex. : Plan de continuité d’activité | B5: Sensible | C5: Direction | D5: DSI / Prestataire informatique
A6: Contacts et dossiers du personnel
A7: Factures clients
A8: Factures fournisseurs
A9: Listes fournisseurs
A10: Données comptables
A11: Relevés de compte
A12: Propositions commerciales
A13: Contrats commerciaux
A14: Contrats de travail
A15: Données de production
A16: Grille tarifaire des produits
A17: Procédés de fabrication
A18: Veille concurrentielle

Sheet A Cartographie
A1: A – Fiche de cartographie des traitements
A2: Complétez la fiche pour FitZone (menus déroulants avec exemples).
A4: Traitement / finalité | B4: Données | C4: Sensibles ? | D4: Personnes concernées | E4: Support | F4: Accès | G4: Durée de conservation | H4: Sous-traitant | I4: Problèmes relevés
A5: Gestion de la paie | B5: Identité | C5: NIR (régime renforcé) | D5: Salariés | E5: Serveur interne | F5: Ressources humaines | G5: 5 ans | H5: Prestataire de paie | I5: Accès limité aux RH (exemple)
A16: Inventaire en 3 niveaux
A17: Niveau | B17: Éléments recensés | I17: Exemple
A18: Actifs primordiaux | I18: Gestion des abonnements, paie, données de santé
A19: Éléments supports | I19: Logiciel de gestion v4.2, Windows Server, Android
A20: Équipements | I20: Serveur, disque USB, smartphones, caméras
A22: Rappel : classez aussi 5 informations de FitZone dans l’onglet « Classif ».

Sheet B Risques
A1: B – Tableau d’analyse de risques
A2: Cotez P et G de 1 à 5 : la criticité et le niveau se calculent seuls.
A4: Réf. | B4: Événement redouté | C4: Critère | D4: Menace | E4: Vulnérabilité | F4: P | G4: G | H4: C = P×G | I4: Niveau
A5: Ex. | B5: Perte d’un ordinateur portable non chiffré | C5: Confidentialité | D5: Erreur interne | E5: Aucun chiffrement | F5: 3 | G5: 3 | H5: =IF(OR(F5="",G5=""),"",F5*G5) -> 9 | I5: =IF(H5="","",IF(H5>=15,"Prioritaire",IF(H5>=10,"À traiter",IF(H5>=5,"À surveiller","Faible")))) -> À surveiller
A6: R1 | H6: =IF(OR(F6="",G6=""),"",F6*G6) | I6: =IF(H6="","",IF(H6>=15,"Prioritaire",IF(H6>=10,"À traiter",IF(H6>=5,"À surveiller","Faible"))))
A7: R2 | H7: =IF(OR(F7="",G7=""),"",F7*G7) | I7: =IF(H7="","",IF(H7>=15,"Prioritaire",IF(H7>=10,"À traiter",IF(H7>=5,"À surveiller","Faible"))))
A8: R3 | H8: =IF(OR(F8="",G8=""),"",F8*G8) | I8: =IF(H8="","",IF(H8>=15,"Prioritaire",IF(H8>=10,"À traiter",IF(H8>=5,"À surveiller","Faible"))))
A9: R4 | H9: =IF(OR(F9="",G9=""),"",F9*G9) | I9: =IF(H9="","",IF(H9>=15,"Prioritaire",IF(H9>=10,"À traiter",IF(H9>=5,"À surveiller","Faible"))))
A10: R5 | H10: =IF(OR(F10="",G10=""),"",F10*G10) | I10: =IF(H10="","",IF(H10>=15,"Prioritaire",IF(H10>=10,"À traiter",IF(H10>=5,"À surveiller","Faible"))))
A11: R6 | H11: =IF(OR(F11="",G11=""),"",F11*G11) | I11: =IF(H11="","",IF(H11>=15,"Prioritaire",IF(H11>=10,"À traiter",IF(H11>=5,"À surveiller","Faible"))))
A12: R7 | H12: =IF(OR(F12="",G12=""),"",F12*G12) | I12: =IF(H12="","",IF(H12>=15,"Prioritaire",IF(H12>=10,"À traiter",IF(H12>=5,"À surveiller","Faible"))))
A13: R8 | H13: =IF(OR(F13="",G13=""),"",F13*G13) | I13: =IF(H13="","",IF(H13>=15,"Prioritaire",IF(H13>=10,"À traiter",IF(H13>=5,"À surveiller","Faible"))))
A15: Au moins un événement par critère (confidentialité, disponibilité, intégrité) et un lié à la preuve. Seuil d’acceptabilité : C ≥ 10.

Sheet C Plan
A1: C – Plan de prévention
A2: Choisissez la réf. du risque : sa criticité s’affiche.
A4: Risque (réf.) | B4: C | C4: Mesure(s) | D4: Couche de défense | E4: Responsable | F4: Prévention | G4: Réparation | H4: État
A5: Ex. | B5: 9 | C5: Sauvegarde 3-2-1 avec copie hors ligne | D5: Donnée | E5: DSI / Prestataire SISR | F5: ✘ À faire | G5: ✘ À faire | H5: Orange
B6: =IF(A6="","",IFERROR(INDEX('B Risques'!$H$6:$H$13,MATCH(A6,'B Risques'!$A$6:$A$13,0)),""))
B7: =IF(A7="","",IFERROR(INDEX('B Risques'!$H$6:$H$13,MATCH(A7,'B Risques'!$A$6:$A$13,0)),""))
B8: =IF(A8="","",IFERROR(INDEX('B Risques'!$H$6:$H$13,MATCH(A8,'B Risques'!$A$6:$A$13,0)),""))
B9: =IF(A9="","",IFERROR(INDEX('B Risques'!$H$6:$H$13,MATCH(A9,'B Risques'!$A$6:$A$13,0)),""))
B10: =IF(A10="","",IFERROR(INDEX('B Risques'!$H$6:$H$13,MATCH(A10,'B Risques'!$A$6:$A$13,0)),""))
B11: =IF(A11="","",IFERROR(INDEX('B Risques'!$H$6:$H$13,MATCH(A11,'B Risques'!$A$6:$A$13,0)),""))
B12: =IF(A12="","",IFERROR(INDEX('B Risques'!$H$6:$H$13,MATCH(A12,'B Risques'!$A$6:$A$13,0)),""))
B13: =IF(A13="","",IFERROR(INDEX('B Risques'!$H$6:$H$13,MATCH(A13,'B Risques'!$A$6:$A$13,0)),""))
A15: La criticité C vient automatiquement du tableau B. Traitez d’abord les 5 risques de criticité la plus élevée.

Sheet Matrice 5x5
A1: Matrice de criticité 5 × 5
A2: Criticité = P × G · seuil d’acceptabilité ≥ 10 · placez vos risques R1…R8
A3: G \ P | B3: 1 | C3: 2 | D3: 3 | E3: 4 | F3: 5
A4: 5 | B4: =$A4*B$3 -> 5 | C4: =$A4*C$3 -> 10 | D4: =$A4*D$3 -> 15 | E4: =$A4*E$3 -> 20 | F4: =$A4*F$3 -> 25
A5: 4 | B5: =$A5*B$3 -> 4 | C5: =$A5*C$3 -> 8 | D5: =$A5*D$3 -> 12 | E5: =$A5*E$3 -> 16 | F5: =$A5*F$3 -> 20
A6: 3 | B6: =$A6*B$3 -> 3 | C6: =$A6*C$3 -> 6 | D6: =$A6*D$3 -> 9 | E6: =$A6*E$3 -> 12 | F6: =$A6*F$3 -> 15
A7: 2 | B7: =$A7*B$3 -> 2 | C7: =$A7*C$3 -> 4 | D7: =$A7*D$3 -> 6 | E7: =$A7*E$3 -> 8 | F7: =$A7*F$3 -> 10
A8: 1 | B8: =$A8*B$3 -> 1 | C8: =$A8*C$3 -> 2 | D8: =$A8*D$3 -> 3 | E8: =$A8*E$3 -> 4 | F8: =$A8*F$3 -> 5
A10: 1–4 Faible · 5–9 À surveiller · 10–14 À traiter · 15–25 Prioritaire

Sheet Listes
A1: Listes des menus déroulants
A2: Vous pouvez compléter ces listes : les menus les relisent.
A4: Catégories | B4: Services | C4: Sensibles | D4: Personnes | E4: Supports | F4: Durées | G4: Sous-traitants | H4: Traitements | I4: Données | J4: Critères | K4: Menaces ANSSI | L4: Menaces | M4: Notes 1-5 | N4: Événements | O4: Vulnérabilités | P4: Couches | Q4: Responsables | R4: Mesures | S4: Actions | T4: États | U4: Qualification | V4: Réfs
A5: Divulgable | B5: Direction | C5: Non | D5: Clients / abonnés | E5: Serveur interne | F5: 1 mois | G5: Aucun | H5: Gestion des abonnements | I5: Identité | J5: Confidentialité | K5: Déstabilisation | L5: Cybercriminalité | M5: 1 | N5: Fuite des certificats médicaux | O5: Dossier partagé ouvert à tous | P5: Politique et procédures | Q5: Direction | R5: Droits d’accès par groupe | S5: ✔ Fait | T5: Rouge | U5: DCP | V5: R1
A6: Sensible | B6: Ressources humaines | C6: Non (financières : vigilance) | D6: Salariés | E6: Cloud / SaaS | F6: 3 mois | G6: Hébergeur | H6: Gestion de la paie | I6: Coordonnées | J6: Disponibilité | K6: Espionnage | L6: Espionnage | M6: 2 | N6: Ransomware chiffrant le serveur et la sauvegarde | O6: Sauvegarde connectée en permanence | P6: Sécurité physique | Q6: DSI / Prestataire SISR | R6: Chiffrement des données | S6: ✘ À faire | T6: Orange | U6: Donnée sensible | V6: R2
A7: Stratégique | B7: Comptabilité / Finance | C7: NIR (régime renforcé) | D7: Candidats | E7: Poste de travail | F7: 1 an | G7: Éditeur SaaS | H7: Suivi d’aptitude médicale | I7: IBAN / RIB | J7: Intégrité | K7: Sabotage | L7: Déstabilisation | M7: 3 | N7: Diffusion d’images des vestiaires | O7: Mot de passe faible ou partagé | P7: DMZ / périmètre | Q7: DPO / référent RGPD | R7: Sauvegarde 3-2-1 avec copie hors ligne | S7: – Sans objet | T7: Vert | U7: Non DCP | V7: R3
B8: Commercial | C8: Oui – santé | D8: Mineurs | E8: Smartphone personnel | F8: 3 ans | G8: Prestataire informatique | H8: Contrôle d’accès biométrique | I8: NIR | J8: Preuve | K8: Cybercriminalité | L8: Sabotage | M8: 4 | N8: Modification d’IBAN sans auteur identifiable | O8: Compte administrateur partagé | P8: Réseau interne | Q8: RH | R8: Test de restauration | V8: R4
B9: Production / Technique | C9: Oui – biométrie | D9: Prestataires | E9: Papier | F9: 5 ans | G9: Prestataire de paie | H9: Newsletter | I9: Photo | J9: Disponibilité + Confidentialité | L9: Sûreté (accident) | M9: 5 | N9: Fuite de la base d’empreintes digitales | O9: Aucune journalisation | P9: Machine | Q9: Comptabilité | R9: Authentification multifacteur (MFA) | V9: R5
B10: DSI / Prestataire informatique | C10: Oui – autre (art. 9) | D10: Visiteurs | E10: Clé USB / disque externe | F10: 10 ans | G10: Autre | H10: Vidéosurveillance | I10: Certificat médical | J10: Intégrité + Preuve | L10: Erreur interne | N10: Panne disque sans sauvegarde valide | O10: Aucun chiffrement | P10: Application | Q10: Tous les salariés | R10: Comptes nominatifs + journalisation | V10: R6
B11: Juridique / DPO | E11: Messagerie / WhatsApp | F11: Durée non définie | H11: Recrutement / CV | I11: Empreinte digitale | L11: Malveillance interne | N11: Perte d’un ordinateur portable non chiffré | O11: Wi-Fi partagé avec l’administration | P11: Donnée | R11: Séparation du Wi-Fi (VLAN) | V11: R7
B12: Tous les salariés | H12: Prospection / CRM | I12: Images vidéo | L12: Fraude interne | N12: E-mail envoyé au mauvais destinataire | O12: Aucun test de restauration | R12: Durée de conservation + purge | V12: R8
B13: Partenaires externes | H13: Gestion des comptes utilisateurs | I13: Données de connexion | O13: Durée de conservation non définie | R13: Alternative badge + AIPD
B14: Public | O14: Correctifs non appliqués | R14: Charte d’usage + sensibilisation
R15: Contrat sous-traitant (art. 28)
